formatter2/__init__.py
formatter2/_stringio.py
formatter2/formatter.py
formatter2/main.py
formatter2/offsets.py
formatter2/tokenize_fork.py
formatter2/tokens.py
formatter2/types.py
formatter2-1.3.0.dist-info/DESCRIPTION.rst
formatter2-1.3.0.dist-info/METADATA
formatter2-1.3.0.dist-info/RECORD
formatter2-1.3.0.dist-info/WHEEL
formatter2-1.3.0.dist-info/entry_points.txt
formatter2-1.3.0.dist-info/metadata.json
formatter2-1.3.0.dist-info/pbr.json
formatter2-1.3.0.dist-info/top_level.txt
tests/__init__.py
tests/base_test.py
tests/test_brace.py
tests/test_commandline.py
tests/test_comment.py
tests/test_formatter.py
tests/test_lists.py
tests/test_operators.py
tests/test_paren.py
tests/test_stdin.py
tests/test_string.py
tests/test_ternary.py
tests/test_tokens.py
tests/test_types.py
