Metadata-Version: 2.0
Name: formatter2
Version: 1.3.0
Summary: A Python source formatter that uses the tokenize library to ensure correctness
Home-page: https://github.com/WoLpH/python-formatter
Author: Rick van Hattem
Author-email: Wolph@wol.ph
License: BSD
Platform: UNKNOWN
Classifier: License :: OSI Approved :: BSD License
Requires-Dist: pep8
